inscreen_sdk_server/__init__.py
inscreen_sdk_server/auth.py
inscreen_sdk_server-0.1.2.dist-info/LICENSE.txt
inscreen_sdk_server-0.1.2.dist-info/METADATA
inscreen_sdk_server-0.1.2.dist-info/WHEEL
inscreen_sdk_server-0.1.2.dist-info/top_level.txt
inscreen_sdk_server-0.1.2.dist-info/RECORD
