Metadata-Version: 2.1
Name: inscreen-sdk-server
Version: 0.1.2
Summary: "inScreen's Python SDK"
Home-page: https://github.com/inscreen/sdk-server/
Author: InScreen, Inc.
Author-email: info@inscreen.com
License: MIT
Project-URL: Documentation, https://github.com/inscreen/sdk-server/tree/main/python
Project-URL: Source, https://github.com/inscreen/sdk-server/tree/main/python
Project-URL: Changelog, https://github.com/inscreen/sdk-server/releases
Platform: any
Classifier: Development Status :: 4 - Beta
Classifier: Programming Language :: Python
License-File: LICENSE.txt
Requires-Dist: pycryptodomex
Requires-Dist: importlib-metadata ; python_version < "3.8"
Provides-Extra: testing
Requires-Dist: setuptools ; extra == 'testing'
Requires-Dist: pytest ; extra == 'testing'
Requires-Dist: pytest-cov ; extra == 'testing'
